octo_infra_aws_python/__init__.py
octo_infra_aws_python/logic/__init__.py
octo_infra_aws_python/logic/ami.py
octo_infra_aws_python/logic/ec2.py
octo_infra_aws_python/logic/network.py
octo_infra_aws_python/logic/s3.py
octo_infra_aws_python/logic/service_discovery.py
octo_infra_aws_python/logic/ssm.py
octo_infra_aws_python/logic/sts.py
octo_infra_aws_python/models/__init__.py
octo_infra_aws_python/models/find_asset.py
octo_infra_aws_python/models/network_rule.py
octo_infra_aws_python/models/regions.py
octo_infra_aws_python/models/service_instance.py
octo_infra_aws_python/models/actions/__init__.py
octo_infra_aws_python/models/actions/ami/__init__.py
octo_infra_aws_python/models/actions/ami/find_image.py
octo_infra_aws_python/models/actions/ec2/__init__.py
octo_infra_aws_python/models/actions/ec2/create_ec2.py
octo_infra_aws_python/models/actions/ec2/create_key_pair.py
octo_infra_aws_python/models/actions/ec2/destroy_ec2.py
octo_infra_aws_python/models/actions/ec2/destroy_key_pair.py
octo_infra_aws_python/models/actions/ec2/find_ec2_instance_password.py
octo_infra_aws_python/models/actions/network/__init__.py
octo_infra_aws_python/models/actions/network/create_internet_gateway.py
octo_infra_aws_python/models/actions/network/create_security_group.py
octo_infra_aws_python/models/actions/network/create_subnet.py
octo_infra_aws_python/models/actions/network/create_vpc.py
octo_infra_aws_python/models/actions/network/destroy_internet_gateway.py
octo_infra_aws_python/models/actions/network/destroy_security_group.py
octo_infra_aws_python/models/actions/network/destroy_subnet.py
octo_infra_aws_python/models/actions/network/destroy_vpc.py
octo_infra_aws_python/models/actions/s3/__init__.py
octo_infra_aws_python/models/actions/s3/delete_objects.py
octo_infra_aws_python/models/actions/s3/download_object.py
octo_infra_aws_python/models/actions/s3/find_objects.py
octo_infra_aws_python/models/actions/s3/load_object.py
octo_infra_aws_python/models/actions/s3/object_exists.py
octo_infra_aws_python-2.0.2.dist-info/LICENSE.txt
octo_infra_aws_python-2.0.2.dist-info/METADATA
octo_infra_aws_python-2.0.2.dist-info/README.md
octo_infra_aws_python-2.0.2.dist-info/WHEEL
octo_infra_aws_python-2.0.2.dist-info/top_level.txt
octo_infra_aws_python-2.0.2.dist-info/RECORD
