Metadata-Version: 2.1
Name: octo-infra-aws-python
Version: 2.0.2
Summary: Octo AWS infra
Home-page: https://github.com/ofiriluz/octo-infra-aws-python
Author: Ofir Iluz
Author-email: iluzofir@gmail.com
License: MIT
Classifier: Intended Audience :: Developers
Classifier: Natural Language :: English
Classifier: Programming Language :: Python
Classifier: Programming Language :: Python :: 3.8
Classifier: Programming Language :: Python :: 3.9
Classifier: Programming Language :: Python :: 3.10
Requires-Python: >= 3.8
License-File: LICENSE.txt
License-File: README.md
Requires-Dist: pydantic
Requires-Dist: boto3
Requires-Dist: boto3-stubs[ec2]
Requires-Dist: boto3-stubs[vpc]
Requires-Dist: boto3-stubs[servicediscovery]
Requires-Dist: boto3-stubs[ssm]
Requires-Dist: boto3-stubs[kms]
Requires-Dist: boto3-stubs[sqs]
Requires-Dist: boto3-stubs[sns]
Requires-Dist: boto3-stubs[sts]
Requires-Dist: boto3-stubs[ecs]
Requires-Dist: boto3-stubs[s3]
Requires-Dist: boto3-stubs[elbv2]
Requires-Dist: boto3-stubs
Requires-Dist: mypy
Requires-Dist: mypy-boto3
Requires-Dist: pycryptodome
